pyopenchannel/__init__.py
pyopenchannel/constants.py
pyopenchannel/design.py
pyopenchannel/exceptions.py
pyopenchannel/flow_analysis.py
pyopenchannel/geometry.py
pyopenchannel/hydraulics.py
pyopenchannel/units.py
pyopenchannel/validators.py
pyopenchannel/gvf/__init__.py
pyopenchannel/gvf/applications.py
pyopenchannel/gvf/profiles.py
pyopenchannel/gvf/solver.py
pyopenchannel/numerical/__init__.py
pyopenchannel/numerical/finite_difference.py
pyopenchannel/numerical/integration.py
pyopenchannel-0.4.0.dist-info/METADATA
pyopenchannel-0.4.0.dist-info/WHEEL
pyopenchannel-0.4.0.dist-info/entry_points.txt
pyopenchannel-0.4.0.dist-info/licenses/LICENSE
pyopenchannel-0.4.0.dist-info/RECORD
