Metadata-Version: 2.4
Name: pyopenchannel
Version: 0.4.0
Summary: A comprehensive Python library for open channel flow analysis and design
Project-URL: Homepage, https://github.com/alexiusacademia/pyopenchannel
Project-URL: Documentation, https://github.com/alexiusacademia/pyopenchannel#readme
Project-URL: Repository, https://github.com/alexiusacademia/pyopenchannel
Project-URL: Issues, https://github.com/alexiusacademia/pyopenchannel/issues
Project-URL: Changelog, https://github.com/alexiusacademia/pyopenchannel/releases
Author-email: Alexius Academia <alexius.sayco.academia@gmail.com>
Maintainer-email: Alexius Academia <alexius.sayco.academia@gmail.com>
License: MIT
License-File: LICENSE
Keywords: channel-design,civil-engineering,hydraulic-engineering,hydraulics,manning-equation,open-channel-flow,water-resources
Classifier: Development Status :: 4 - Beta
Classifier: Intended Audience :: Education
Classifier: Intended Audience :: Science/Research
Classifier: License :: OSI Approved :: MIT License
Classifier: Operating System :: OS Independent
Classifier: Programming Language :: Python :: 3
Classifier: Programming Language :: Python :: 3.9
Classifier: Programming Language :: Python :: 3.10
Classifier: Programming Language :: Python :: 3.11
Classifier: Programming Language :: Python :: 3.12
Classifier: Programming Language :: Python :: 3.13
Classifier: Topic :: Education
Classifier: Topic :: Scientific/Engineering
Classifier: Topic :: Scientific/Engineering :: Physics
Classifier: Typing :: Typed
Requires-Python: >=3.9
Provides-Extra: dev
Requires-Dist: black>=23.0.0; extra == 'dev'
Requires-Dist: flake8>=6.0.0; extra == 'dev'
Requires-Dist: isort>=5.12.0; extra == 'dev'
Requires-Dist: mypy>=1.0.0; extra == 'dev'
Requires-Dist: pre-commit>=3.0.0; extra == 'dev'
Requires-Dist: pytest-cov>=4.0.0; extra == 'dev'
Requires-Dist: pytest-timeout>=2.1.0; extra == 'dev'
Requires-Dist: pytest>=7.0.0; extra == 'dev'
Provides-Extra: docs
Requires-Dist: myst-parser>=1.0.0; extra == 'docs'
Requires-Dist: sphinx-rtd-theme>=1.2.0; extra == 'docs'
Requires-Dist: sphinx>=6.0.0; extra == 'docs'
Provides-Extra: examples
Requires-Dist: matplotlib>=3.6.0; extra == 'examples'
Requires-Dist: numpy>=1.24.0; extra == 'examples'
Provides-Extra: test
Requires-Dist: pytest-cov>=4.0.0; extra == 'test'
Requires-Dist: pytest-timeout>=2.1.0; extra == 'test'
Requires-Dist: pytest>=7.0.0; extra == 'test'
